{
  "version": "1.0.0",
  "description": "Standard property name mapping and unit normalization rules ported from v4 property_catalog.md (NFM-524)",
  "property_aliases": {
    "density": "密度",
    "theoretical density": "理论密度",
    "relative density": "相对密度",
    "specific heat": "比热容",
    "heat capacity": "比热容",
    "heat capacity at constant pressure": "定压比热容",
    "Cp": "定压比热容",
    "thermal conductivity": "热导率",
    "thermal diffusivity": "热扩散率",
    "thermal resistance": "热阻",
    "Young's modulus": "杨氏模量",
    "elastic modulus": "杨氏模量",
    "shear modulus": "剪切模量",
    "bulk modulus": "体积模量",
    "Poisson's ratio": "泊松比",
    "elastic constants": "弹性常数",
    "stiffness tensor": "弹性常数",
    "yield strength": "屈服强度",
    "yield stress": "屈服强度",
    "tensile strength": "抗拉强度",
    "UTS": "抗拉强度",
    "ultimate strength": "抗拉强度",
    "flow stress": "流动应力",
    "fracture strain": "断裂应变",
    "burst strain": "断裂应变",
    "elongation": "延伸率",
    "ductility": "延伸率",
    "Ramberg-Osgood": "Ramberg-Osgood参数",
    "Johnson-Cook": "Johnson-Cook参数",
    "yield criterion": "屈服准则参数",
    "constitutive parameter": "本构模型参数",
    "material constant": "本构模型参数",
    "mean thermal expansion": "平均线膨胀系数",
    "average CTE": "平均线膨胀系数",
    "instantaneous thermal expansion": "瞬时线膨胀系数",
    "instantaneous CTE": "瞬时线膨胀系数",
    "thermal expansion strain": "热膨胀应变",
    "volumetric thermal expansion": "体膨胀系数",
    "creep strain": "蠕变应变",
    "irradiation creep strain": "蠕变应变",
    "creepdown strain": "蠕变应变",
    "steady-state creep rate": "稳态蠕变速率",
    "transient creep rate": "瞬态蠕变速率",
    "irradiation creep rate": "辐照蠕变速率",
    "creep compliance": "蠕变柔量",
    "stress exponent": "应力指数",
    "creep exponent": "应力指数",
    "Norton creep": "Norton蠕变参数",
    "creep law parameter": "Norton蠕变参数",
    "time-to-failure": "失效时间",
    "rupture time": "失效时间",
    "volume swelling": "体积膨胀率",
    "void swelling": "空洞肿胀率",
    "gas bubble swelling": "气泡肿胀率",
    "dimensional change": "尺寸变化率",
    "irradiation growth": "尺寸变化率",
    "average void size": "平均空洞尺寸",
    "mean void diameter": "平均空洞尺寸",
    "void density": "空洞密度",
    "bubble density": "气泡密度",
    "bubble number density": "气泡密度",
    "corrosion rate": "腐蚀速率",
    "oxidation rate": "氧化速率",
    "oxide thickness": "氧化膜厚度",
    "oxide layer thickness": "氧化膜厚度",
    "weight gain": "氧化增重",
    "mass gain": "氧化增重",
    "hydrogen pickup": "吸氢率",
    "H pickup fraction": "吸氢率",
    "hydrogen content": "氢含量",
    "H content": "氢含量",
    "deuterium uptake": "吸氘率",
    "deuterium pickup": "吸氘率",
    "deuterium content": "氘含量",
    "D content": "氘含量",
    "SCC threshold": "应力腐蚀阈值",
    "stress corrosion cracking threshold": "应力腐蚀阈值",
    "crack growth rate": "裂纹扩展速率",
    "corrosion fatigue crack growth rate": "腐蚀疲劳裂纹扩展速率",
    "pitting density": "点蚀密度",
    "pit density": "点蚀密度",
    "hardness": "硬度",
    "Vickers hardness": "硬度",
    "microhardness": "硬度",
    "hardening modulus": "硬化模量",
    "strain hardening exponent": "硬化指数",
    "irradiation hardening": "辐照硬化量",
    "yield strength increase": "辐照硬化量",
    "strength increment": "强度增量",
    "increase in yield stress": "强度增量",
    "dislocation hardening parameter": "位错硬化参数",
    "outside diameter": "样品外径",
    "inside diameter": "样品内径",
    "wall thickness": "壁厚",
    "fuelled length": "燃料段长度",
    "fuel segment length": "燃料段长度",
    "cold work": "冷加工量",
    "cold reduction": "冷加工量",
    "annealing temperature": "热处理温度",
    "heat treatment temperature": "热处理温度",
    "extrusion temperature": "挤压温度",
    "grain size": "晶粒尺寸",
    "phase fraction": "相分数",
    "volume fraction": "相分数",
    "precipitate size": "析出相尺寸",
    "SPP size": "析出相尺寸",
    "dislocation density": "位错密度",
    "lattice parameter a": "晶格参数a",
    "lattice parameter c": "晶格参数c",
    "interplanar distance": "晶面间距",
    "d-spacing": "晶面间距",
    "texture coefficient": "织构系数",
    "Kearns factor": "织构系数"
  },
  "unit_normalization": {
    "um": "μm",
    "µm": "μm",
    "percent": "%",
    "deg c": "°C",
    "degrees c": "°C",
    "angstrom": "Å",
    "m2": "m²",
    "m^2": "m²",
    "s-1": "s⁻¹",
    "s^-1": "s⁻¹"
  }
}
